vocalize/__init__.py
vocalize/py.typed
vocalize/conversation/__init__.py
vocalize/conversation/built_in.py
vocalize/conversation/conversation.py
vocalize/conversation/message.py
vocalize/conversation/role.py
vocalize/flow/__init__.py
vocalize/flow/events.py
vocalize/flow/flow.py
vocalize/flow/flowstep.py
vocalize/interrupter/__init__.py
vocalize/interrupter/cancellable.py
vocalize/interrupter/interrupter.py
vocalize/llm/__init__.py
vocalize/llm/config.py
vocalize/llm/llm.py
vocalize/log/propogate.py
vocalize/phone/__init__.py
vocalize/phone/call.py
vocalize/phone/phone.py
vocalize/queues/__init__.py
vocalize/queues/queues.py
vocalize/stt/__init__.py
vocalize/stt/deepgram.py
vocalize/stt/stt.py
vocalize/tests/llm_test.py
vocalize/tests/test_cartesia_encoding_format.py
vocalize/tests/test_flow.py
vocalize/tests/test_stt.py
vocalize/tests/fixtures/__init__.py
vocalize/tests/fixtures/initialize.py
vocalize/tests/fixtures/skeleton.py
vocalize/tests/latency/__init__.py
vocalize/tests/latency/test_deepgram.py
vocalize/tests/latency/test_eleven_labs.py
vocalize/tests/sample_data/audio.wav
vocalize/tts/__init__.py
vocalize/tts/cartesia_custom.py
vocalize/tts/eleven_labs.py
vocalize/tts/tts.py
vocalize-0.0.7.dist-info/METADATA
vocalize-0.0.7.dist-info/WHEEL
vocalize-0.0.7.dist-info/licenses/LICENSE
vocalize-0.0.7.dist-info/RECORD
