Metadata-Version: 2.3
Name: vocalize
Version: 0.0.7
Summary: A library to simply and easily have conversations with AI Agents.
Project-URL: homepage, https://github.com/damonguzman/vocalize
Project-URL: issues, https://github.com/damonguzman/vocalize/issues
Author-email: Damon Guzman <damonguzman.dev@gmail.com>
License-File: LICENSE
Classifier: License :: OSI Approved :: MIT License
Classifier: Operating System :: OS Independent
Classifier: Programming Language :: Python :: 3
Requires-Python: >=3.11
Requires-Dist: cartesia
Requires-Dist: httpx
Requires-Dist: loguru
Requires-Dist: pydantic
Requires-Dist: websockets
